vtt2txt/__about__.py
vtt2txt/__init__.py
vtt2txt/__main__.py
vtt2txt_ng-0.0.4.dist-info/METADATA
vtt2txt_ng-0.0.4.dist-info/WHEEL
vtt2txt_ng-0.0.4.dist-info/entry_points.txt
vtt2txt_ng-0.0.4.dist-info/licenses/LICENSE.txt
vtt2txt_ng-0.0.4.dist-info/RECORD
