Metadata-Version: 2.4
Name: vtt2txt-ng
Version: 0.0.4
Summary: Convert VTT subtitles file to a plain text file
Project-URL: Documentation, https://github.com/lrq3000/vtt2txt-ng#readme
Project-URL: Issues, https://github.com/lrq3000/vtt2txt-ng/issues
Project-URL: Source, https://github.com/lrq3000/vtt2txt-ng
Author-email: Stephen Karl Larroque <lrq3000@gmail.com>, Trey Hunner <trey@treyhunner.com>
License-Expression: MIT
License-File: LICENSE.txt
Classifier: Development Status :: 4 - Beta
Classifier: Programming Language :: Python
Classifier: Programming Language :: Python :: 3.7
Classifier: Programming Language :: Python :: 3.8
Classifier: Programming Language :: Python :: 3.9
Classifier: Programming Language :: Python :: 3.10
Classifier: Programming Language :: Python :: 3.11
Classifier: Programming Language :: Python :: 3.12
Classifier: Programming Language :: Python :: Implementation :: CPython
Classifier: Programming Language :: Python :: Implementation :: PyPy
Requires-Python: >=3.7
